{"schema":"spec/0.1","type":"ad.string.bank","id":"ad.string.bank-1767074780647-prop.value","payload":{"bankId":"prop.value","offset":35001,"strings":["Track: (Net: PCIE_TXN0 Width:5mil Length:210.549mil)","Track (4555.967mil,1725.537mil)(4555.971mil,1725.541mil) on L8","Track: (Net: PCIE_TXN1 Width:5mil Length:0.006mil)","Track (4474.075mil,1596.25mil)(4557.79mil,1659.99mil) on L8","Track: (Net: PCIE_TXN1 Width:5mil Length:105.219mil)","Track (4433.001mil,1547.116mil)(4454.846mil,1576.726mil) on L8","Track: (Net: PCIE_TXN1 Width:5mil Length:36.796mil)","Track (2753.938mil,1309.001mil)(2753.938mil,1309.001mil) on L8","Track: (Net: PCIE_TXN1 Width:5mil Length:0mil)","Track (2649.5mil,1258.5mil)(2661.86mil,1270.86mil) on L8","Track: (Net: PCIE_TXN1 Width:5mil Length:17.48mil)","Track (4290.488mil,1511.475mil)(4362.418mil,1511.475mil) on L8","Track: (Net: PCIE_TXN1 Width:5mil Length:71.93mil)","Track (4479.528mil,1589.09mil)(4563.242mil,1652.83mil) on L8","Track: (Net: PCIE_TXP1 Width:5mil Length:105.217mil)","Track (4362.418mil,1502.475mil)(4362.418mil,1502.475mil) on L8","Track: (Net: PCIE_TXP1 Width:5mil Length:0mil)","Track (2754.061mil,1300.001mil)(3353.893mil,1300.001mil) on L8","Track: (Net: PCIE_TXP1 Width:5mil Length:599.832mil)","Track (2655.804mil,1252.076mil)(2668.138mil,1264.41mil) on L8","Track: (Net: PCIE_TXP1 Width:5mil Length:17.444mil)","Track (4115.852mil,1381.548mil)(4115.854mil,1381.548mil) on L8","Track: (Net: PCIE_TXN1 Width:5mil Length:0.002mil)","Track (2782.541mil,1309.001mil)(2926.261mil,1309mil) on L8","Track: (Net: PCIE_TXN1 Width:5mil Length:143.72mil)","Track (2116.926mil,1236.058mil)(2117.621mil,1236.058mil) on L8","Track: (Net: PCIE_TXN1 Width:5mil Length:0.695mil)","Track (4586.614mil,1700mil)(4586.614mil,1725.881mil) on L8","Track: (Net: PCIE_TXP1 Width:5mil Length:25.881mil)","Track (4113.936mil,1366.903mil)(4119.581mil,1372.548mil) on L8","Track: (Net: PCIE_TXP1 Width:5mil Length:7.983mil)","Track (3353.893mil,1300.001mil)(3353.894mil,1300mil) on L8","Track: (Net: PCIE_TXP1 Width:5mil Length:0.001mil)","Track (2116.926mil,1227.058mil)(2117.621mil,1227.058mil) on L8","Track: (Net: PCIE_TXP1 Width:5mil Length:0.695mil)","Track (4480.475mil,1682.475mil)(4482.253mil,1684.253mil) on L8","Track: (Net: PCIE_TXN0 Width:5mil Length:2.515mil)","Track (4493.713mil,1689mil)(4504.757mil,1689mil) on L8","Track: (Net: PCIE_TXN0 Width:5mil Length:11.044mil)","Track (4488.19mil,1730.078mil)(4494.193mil,1730.078mil) on L8","Track: (Net: PCIE_TXN0 Width:5mil Length:6.003mil)","Track (2197.505mil,1336.26mil)(2197.847mil,1336.26mil) on L8","Track: (Net: PCIE_TXN0 Width:5mil Length:0.342mil)","Track (2173.086mil,1308.962mil)(2173.086mil,1308.961mil) on L8","Track: (Net: PCIE_TXN0 Width:5mil Length:0.001mil)","Track (4318.666mil,1587.476mil)(4371mil,1587.476mil) on L8","Track: (Net: PCIE_TXP0 Width:5mil Length:52.334mil)","Track (2197.432mil,1345.26mil)(2197.433mil,1345.261mil) on L8","Track: (Net: PCIE_TXP0 Width:5mil Length:0.001mil)","Track (4431.562mil,1612.562mil)(4453.218mil,1634.218mil) on L8","Track: (Net: PCIE_TXP0 Width:5mil Length:30.626mil)","Track (2468.644mil,1357.761mil)(2468.644mil,1370.999mil) on L8","Track: (Net: PCIE_TXN0 Width:5mil Length:13.239mil)","Track (2772.69mil,1336.26mil)(2772.691mil,1336.261mil) on L8","Track (2712.213mil,1336.26mil)(2772.69mil,1336.26mil) on L8","Track: (Net: PCIE_TXN0 Width:5mil Length:60.477mil)","Track (2197.847mil,1336.26mil)(2197.847mil,1336.26mil) on L8","Track (2374.851mil,1336.26mil)(2431.085mil,1336.26mil) on L8","Track: (Net: PCIE_TXN0 Width:5mil Length:56.235mil)","Track (2201.161mil,1336.26mil)(2204.847mil,1336.26mil) on L8","Track: (Net: PCIE_TXN0 Width:5mil Length:3.687mil)","Track (2201.16mil,1336.26mil)(2201.161mil,1336.26mil) on L8","Track (2536.646mil,1309.915mil)(2536.646mil,1370.707mil) on L8","Track: (Net: PCIE_TXN0 Width:5mil Length:60.793mil)","Track (2319.349mil,1309.915mil)(2319.349mil,1370.707mil) on L8","Track (2493.644mil,1309.915mil)(2493.644mil,1370.999mil) on L8","Track: (Net: PCIE_TXN0 Width:5mil Length:61.085mil)","Track (2251.348mil,1309.915mil)(2251.348mil,1370.707mil) on L8","Track (4485.394mil,1766.652mil)(4488.19mil,1769.448mil) on L8","Track: (Net: PCIE_TXP0 Width:5mil Length:3.954mil)","Track (3933.575mil,1345.261mil)(3933.575mil,1345.261mil) on L8","Track: (Net: PCIE_TXP0 Width:5mil Length:0mil)","Track (2459.644mil,1357.761mil)(2459.644mil,1370.999mil) on L8","Track: (Net: PCIE_TXP0 Width:5mil Length:13.239mil)","Track (2440.143mil,1345.261mil)(2447.144mil,1345.261mil) on L8","Track: (Net: PCIE_TXP0 Width:5mil Length:7.001mil)","Track (2217.347mil,1357.761mil)(2217.347mil,1370.707mil) on L8","Track: (Net: PCIE_TXP0 Width:5mil Length:12.947mil)","Track (2374.851mil,1345.261mil)(2431.085mil,1345.261mil) on L8","Track: (Net: PCIE_TXP0 Width:5mil Length:56.235mil)","Track (2431.085mil,1345.261mil)(2440.143mil,1345.261mil) on L8","Track: (Net: PCIE_TXP0 Width:5mil Length:9.058mil)","Track (2527.645mil,1309.915mil)(2527.645mil,1370.707mil) on L8","Track: (Net: PCIE_TXP0 Width:5mil Length:60.793mil)","Track (2328.35mil,1309.915mil)(2328.35mil,1370.707mil) on L8","Track (2502.645mil,1309.915mil)(2502.645mil,1370.999mil) on L8","Track: (Net: PCIE_TXP0 Width:5mil Length:61.085mil)","Track (2260.349mil,1309.915mil)(2260.349mil,1370.707mil) on L8","Track (659.536mil,3713.464mil)(659.536mil,3801.536mil) on L8","Track: (Net: KGND Width:15mil Length:88.072mil)","Track (708.662mil,3850.662mil)(708.662mil,3996.89mil) on L8","Track: (Net: KGND Width:15mil Length:146.228mil)","Track (1763.183mil,1932.558mil)(1763.184mil,1932.559mil) on L8","Track: (Net: FPGA_DONE Width:4.8mil Length:0.001mil)","Track (1700.753mil,1932.558mil)(1723.813mil,1932.558mil) on L8","Track: (Net: FPGA_DONE Width:4.8mil Length:23.061mil)","Track (1818.863mil,1932.558mil)(1841.923mil,1932.558mil) on L8","Track (1700.752mil,1932.559mil)(1700.753mil,1932.558mil) on L8","Track (1802.553mil,1932.558mil)(1802.554mil,1932.559mil) on L8","Track (1818.862mil,1932.559mil)(1818.863mil,1932.558mil) on L8","Track (1802.554mil,1932.559mil)(1818.862mil,1932.559mil) on L8","Track: (Net: FPGA_DONE Width:4.8mil Length:16.307mil)","Track (1841.923mil,1932.558mil)(1841.924mil,1932.559mil) on L8","Track (1779.492mil,1932.559mil)(1779.493mil,1932.558mil) on L8","Track (1779.493mil,1932.558mil)(1802.553mil,1932.558mil) on L8","Track (1869.762mil,1904.72mil)(1869.762mil,1921.028mil) on L8","Track: (Net: FPGA_DONE Width:4.8mil Length:16.308mil)","Track (1763.184mil,1932.559mil)(1779.492mil,1932.559mil) on L8","Track (7275mil,1219.543mil)(7413.8mil,1080.743mil) on L8","Track: (Net: KGND Width:15mil Length:196.293mil)","Track (7275mil,1219.543mil)(7275mil,1330mil) on L8","Track: (Net: KGND Width:15mil Length:110.457mil)","Track (4448.818mil,2911.182mil)(4488.188mil,2871.812mil) on L8","Track: (Net: CPU1_LCS01 Width:4.8mil Length:55.678mil)","Track (4570mil,898.071mil)(4570mil,970mil) on L8","Track: (Net: CPU1_IIC1_SCL Width:4.8mil Length:71.929mil)","Track (4590mil,969.635mil)(4850.986mil,1230.621mil) on L8","Track: (Net: CPU1_IIC1_SDA Width:4.8mil Length:369.09mil)","Track (4836mil,1236mil)(4836mil,1365.329mil) on L8","Track: (Net: CPU1_IIC1_SCL Width:4.8mil Length:129.329mil)","Track (4570mil,752.755mil)(4570mil,898.071mil) on L8","Track: (Net: CPU1_IIC1_SCL Width:4.8mil Length:145.316mil)","Track (4525.355mil,708.11mil)(4570mil,752.755mil) on L8","Track: (Net: CPU1_IIC1_SCL Width:4.8mil Length:63.137mil)","Track (4109.61mil,708.11mil)(4525.355mil,708.11mil) on L8","Track: (Net: CPU1_IIC1_SCL Width:4.8mil Length:415.745mil)","Track (3966.77mil,544.905mil)(4079.975mil,658.11mil) on L8","Track: (Net: CPU1_IIC1_SDA Width:4.8mil Length:160.096mil)","Track (4598.11mil,658.11mil)(4904.626mil,658.11mil) on L8","Track: (Net: 1V05PGOOD_TEMP Width:4.8mil Length:306.516mil)","Track (4191.29mil,594.39mil)(4534.39mil,594.39mil) on L8","Track: (Net: 1V05PGOOD_TEMP Width:4.8mil Length:343.1mil)","Track (3937.78mil,301.536mil)(3937.78mil,536.28mil) on L8","Track: (Net: CPU1_IIC1_SCL Width:4.8mil Length:234.744mil)","Track (6686.5mil,67.5mil)(6830.594mil,67.5mil) on L8","Track: (Net: +5V Width:15mil Length:144.094mil)","Track (6640mil,114mil)(6686.5mil,67.5mil) on L8","Track: (Net: +5V Width:15mil Length:65.761mil)","Track (6971.212mil,235.695mil)(6971.212mil,1854.788mil) on L8","Track: (Net: CPU1_JTAG_TRST Width:4.8mil Length:1619.093mil)","Track (6806.583mil,107.5mil)(6843.017mil,107.5mil) on L8","Track: (Net: CPU1_JTAG_TRST Width:4.8mil Length:36.434mil)","Track (6159.854mil,241.146mil)(6287mil,114mil) on L8","Track: (Net: +5V Width:15mil Length:179.812mil)","Track (7090.354mil,327.26mil)(7090.354mil,502.756mil) on L8","Track: (Net: +5V Width:15mil Length:175.496mil)","Track (6299.756mil,1202.756mil)(6310.2mil,1213.2mil) on L8","Track: (Net: CPU1_JTAG_HRESET Width:4.8mil Length:14.77mil)","Track (6310.2mil,1213.2mil)(6310.2mil,2499.014mil) on L8","Track: (Net: CPU1_JTAG_HRESET Width:4.8mil Length:1285.814mil)","Track (6324.6mil,1182.902mil)(6324.6mil,1202.756mil) on L8","Track: (Net: CPU1_JTAG_SRESET Width:4.8mil Length:19.854mil)","Track (6280mil,1138.302mil)(6324.6mil,1182.902mil) on L8","Track: (Net: CPU1_JTAG_SRESET Width:4.8mil Length:63.074mil)","Track (6271mil,1129.302mil)(6280mil,1138.302mil) on L8","Track: (Net: CPU1_JTAG_SRESET Width:4.8mil Length:12.728mil)","Track (6228.112mil,569.525mil)(6228.112mil,683.939mil) on L8","Track: (Net: CPU1_JTAG_SRESET Width:4.8mil Length:114.415mil)","Track (6228.112mil,683.939mil)(6232.588mil,688.415mil) on L8","Track: (Net: CPU1_JTAG_SRESET Width:4.8mil Length:6.33mil)","Track (6213.712mil,563.56mil)(6218.188mil,559.084mil) on L8","Track: (Net: CPU1_JTAG_HRESET Width:4.8mil Length:6.33mil)","Track (6213.712mil,563.56mil)(6213.712mil,689.904mil) on L8","Track: (Net: CPU1_JTAG_HRESET Width:4.8mil Length:126.344mil)","Track (6233.11mil,471.733mil)(6233.11mil,564.527mil) on L8","Track: (Net: CPU1_JTAG_SRESET Width:4.8mil Length:92.794mil)","Track (6218.188mil,435.812mil)(6218.188mil,559.084mil) on L8","Track: (Net: CPU1_JTAG_HRESET Width:4.8mil Length:123.272mil)","Track (6120.304mil,1054.77mil)(6295.8mil,1230.267mil) on L8","Track: (Net: 2V5PGOOD_TEMP Width:4.8mil Length:248.189mil)","Track (6210.788mil,2401.574mil)(6266.139mil,2346.223mil) on L8","Track: (Net: 1V4PGOOD_TEMP Width:4.8mil Length:78.278mil)","Track (6234.409mil,2417.323mil)(6280.539mil,2371.193mil) on L8","Track: (Net: 3V3PGOOD_TEMP Width:4.8mil Length:65.237mil)","Track (6005.007mil,1010.4mil)(6266.139mil,1271.532mil) on L8","Track: (Net: 1V4PGOOD_TEMP Width:4.8mil Length:369.296mil)","Track (6234.507mil,1770.098mil)(6250.47mil,1786.061mil) on L8","Track: (Net: CPU1_A12 Width:4.8mil Length:22.575mil)","Track (6233.07mil,1753.898mil)(6234.507mil,1755.335mil) on L8","Track: (Net: CPU1_A12 Width:4.8mil Length:2.033mil)","Track (6233.597mil,1996.597mil)(6250.47mil,1979.723mil) on L8","Track: (Net: CPU1_A12 Width:4.8mil Length:23.863mil)","Track (5544.686mil,1056.548mil)(5544.686mil,1900.407mil) on L8","Track: (Net: CPU1_706_WDI Width:4.8mil Length:843.86mil)","Track (5501.486mil,1074.442mil)(5501.486mil,1918.301mil) on L8","Track: (Net: 7998_CONVST Width:4.8mil Length:843.86mil)","Track (5501.486mil,1918.301mil)(5626.984mil,2043.8mil) on L8","Track: (Net: 7998_CONVST Width:4.8mil Length:177.482mil)","Track (5515.886mil,1068.477mil)(5515.886mil,1912.337mil) on L8","Track: (Net: CPU1_706_RESET Width:4.8mil Length:843.86mil)","Track (5487.086mil,1080.406mil)(5487.086mil,1924.266mil) on L8","Track: (Net: 7998_ALERT Width:4.8mil Length:843.86mil)","Track (5433.36mil,1486.59mil)(5458.286mil,1461.664mil) on L8","Track: (Net: 1V05PGOOD_TEMP Width:4.8mil Length:35.25mil)","Track (5458.286mil,1092.335mil)(5458.286mil,1461.664mil) on L8","Track: (Net: 1V05PGOOD_TEMP Width:4.8mil Length:369.329mil)","Track (5544mil,1055.862mil)(5544.686mil,1056.548mil) on L8","Track: (Net: CPU1_706_WDI Width:4.8mil Length:0.97mil)","Track (5464.6mil,1078.285mil)(5472.686mil,1086.371mil) on L8","Track: (Net: 1V5PGOOD_TEMP Width:4.8mil Length:11.435mil)","Track (5404.409mil,957mil)(5515.886mil,1068.477mil) on L8","Track: (Net: CPU1_706_RESET Width:4.8mil Length:157.652mil)","Track (5380.55mil,1014.6mil)(5458.286mil,1092.335mil) on L8","Track: (Net: 1V05PGOOD_TEMP Width:4.8mil Length:109.934mil)","Track (5419.835mil,928.2mil)(5544mil,1052.365mil) on L8","Track: (Net: CPU1_706_WDI Width:4.8mil Length:175.595mil)","Track (5544mil,1052.365mil)(5544mil,1055.862mil) on L8","Track: (Net: CPU1_706_WDI Width:4.8mil Length:3.498mil)","Track (5198.529mil,985.8mil)(5392.48mil,985.8mil) on L8","Track: (Net: 7998_ALERT Width:4.8mil Length:193.95mil)","Track (5559.086mil,1047.086mil)(5559.086mil,1800.031mil) on L8","Track: (Net: CPU1_706_MR Width:4.8mil Length:752.945mil)","Track (5228.8mil,913.8mil)(5425.8mil,913.8mil) on L8","Track: (Net: CPU1_706_MR Width:4.8mil Length:197mil)","Track (5386.515mil,1000.2mil)(5464.6mil,1078.285mil) on L8","Track: (Net: 1V5PGOOD_TEMP Width:4.8mil Length:110.429mil)","Track (5939.415mil,2141.732mil)(5954.883mil,2157.2mil) on L8","Track: (Net: CPU1_706_MR Width:4.8mil Length:21.875mil)","Track (5677.449mil,1986mil)(5783.683mil,1986mil) on L8","Track: (Net: CPU1_706_MR Width:4.8mil Length:106.234mil)","Track (5684.001mil,2043.8mil)(5781.933mil,2141.732mil) on L8","Track: (Net: 7998_CONVST Width:4.8mil Length:138.497mil)","Track (5644.878mil,2000.6mil)(5742.605mil,2000.6mil) on L8","Track: (Net: CPU1_706_WDI Width:4.8mil Length:97.727mil)","Track (5733.942mil,2015mil)(5860.675mil,2141.732mil) on L8","Track: (Net: CPU1_706_WDO Width:4.8mil Length:179.226mil)","Track (5742.605mil,2000.6mil)(5883.738mil,2141.732mil) on L8","Track: (Net: CPU1_706_WDI Width:4.8mil Length:199.591mil)","Track (5659.031mil,2058.2mil)(5742.563mil,2141.732mil) on L8","Track: (Net: 7998_ALERT Width:4.8mil Length:118.132mil)","Track (5433.36mil,1486.59mil)(5433.36mil,1911.269mil) on L8","Track: (Net: 1V05PGOOD_TEMP Width:4.8mil Length:424.679mil)","Track (5447.76mil,1492.555mil)(5447.76mil,1905.305mil) on L8","Track: (Net: 1V5PGOOD_TEMP Width:4.8mil Length:412.75mil)","Track (5883.738mil,2141.732mil)(5927.044mil,2185.039mil) on L8","Track: (Net: CPU1_706_WDI Width:4.8mil Length:61.245mil)","Track (5876.141mil,2157.199mil)(5876.141mil,2173.506mil) on L8","Track: (Net: CPU1_706_WDO Width:4.8mil Length:16.307mil)","Track (6112.363mil,2314.68mil)(6112.363mil,2724.69mil) on L8","Track: (Net: CPU1_706_MR Width:4.8mil Length:410.009mil)","Track (6045.154mil,2263.779mil)(6061.462mil,2263.779mil) on L8","Track: (Net: CPU1_706_MR Width:4.8mil Length:16.307mil)","Track (6072.993mil,2275.31mil)(6072.993mil,2291.617mil) on L8","Track (5994.253mil,2212.877mil)(6005.785mil,2224.409mil) on L8","Track: (Net: CPU1_706_MR Width:4.8mil Length:16.308mil)","Track (6100.832mil,2303.149mil)(6112.363mil,2314.68mil) on L8","Track (5966.415mil,2185.039mil)(5982.722mil,2185.039mil) on L8","Track (5954.883mil,2157.2mil)(5954.883mil,2173.507mil) on L8","Track (6022.092mil,2224.409mil)(6033.623mil,2235.94mil) on L8","Track (6033.623mil,2252.248mil)(6045.154mil,2263.779mil) on L8","Track (5994.253mil,2235.94mil)(5994.253mil,2252.247mil) on L8","Track: (Net: CPU1_706_WDI Width:4.8mil Length:16.307mil)","Track (5954.883mil,2196.57mil)(5954.883mil,2212.878mil) on L8","Track (5943.352mil,2185.039mil)(5954.883mil,2196.57mil) on L8","Track: (Net: CPU1_706_WDI Width:4.8mil Length:16.308mil)","Track (6033.623mil,2291.617mil)(6045.155mil,2303.149mil) on L8","Track (6022.092mil,2263.779mil)(6033.623mil,2275.31mil) on L8","Track (6061.462mil,2303.149mil)(6072.993mil,2314.68mil) on L8","Track (6033.623mil,2275.31mil)(6033.623mil,2291.617mil) on L8","Track (6033.623mil,2314.68mil)(6033.623mil,2696.851mil) on L8","Track: (Net: CPU1_706_WDO Width:4.8mil Length:382.171mil)","Track (5982.722mil,2263.779mil)(5994.253mil,2275.31mil) on L8","Track: (Net: CPU1_706_WDO Width:4.8mil Length:16.308mil)","Track (5994.253mil,2275.31mil)(5994.253mil,2291.618mil) on L8","Track (5943.352mil,2224.409mil)(5954.883mil,2235.94mil) on L8","Track (5927.044mil,2224.409mil)(5943.352mil,2224.409mil) on L8","Track (5876.141mil,2173.506mil)(5927.044mil,2224.409mil) on L8","Track: (Net: CPU1_706_WDO Width:4.8mil Length:71.988mil)","Track (5994.253mil,2657.481mil)(6013.938mil,2677.166mil) on L8","Track: (Net: CPU1_706_RESET Width:4.8mil Length:27.839mil)","Track (5982.722mil,2303.149mil)(5994.253mil,2314.68mil) on L8","Track: (Net: CPU1_706_RESET Width:4.8mil Length:16.308mil)","Track (5954.883mil,2291.617mil)(5966.415mil,2303.149mil) on L8","Track (5943.352mil,2263.779mil)(5954.883mil,2275.31mil) on L8","Track (5895.827mil,2232.562mil)(5927.044mil,2263.779mil) on L8","Track: (Net: CPU1_706_RESET Width:4.8mil Length:44.148mil)","Track (5864.61mil,2185.039mil)(5895.827mil,2216.256mil) on L8","Track (5836.771mil,2173.508mil)(5848.302mil,2185.039mil) on L8","Track (5135.6mil,882.142mil)(5210.458mil,957mil) on L8","Track: (Net: CPU1_706_RESET Width:4.8mil Length:105.866mil)","Track (5037.071mil,456.439mil)(5135.6mil,554.968mil) on L8","Track: (Net: CPU1_706_RESET Width:4.8mil Length:139.342mil)","Track (4125.988mil,136.012mil)(4759.012mil,136.012mil) on L8","Track: (Net: CPU1_706_RESET Width:4.8mil Length:633.024mil)","Track (3496.136mil,232.868mil)(4029.132mil,232.868mil) on L8","Track: (Net: CPU1_706_RESET Width:4.8mil Length:532.996mil)","Track (3479.528mil,216.26mil)(3496.136mil,232.868mil) on L8","Track: (Net: CPU1_706_RESET Width:4.8mil Length:23.487mil)","Track (5150mil,876.177mil)(5216.423mil,942.6mil) on L8","Track: (Net: CPU1_706_WDO Width:4.8mil Length:93.936mil)","Track (5055.2mil,408.2mil)(5055.2mil,448.929mil) on L8","Track: (Net: CPU1_706_WDO Width:4.8mil Length:40.729mil)","Track (3867.426mil,191.574mil)(3895.883mil,163.117mil) on L8","Track: (Net: CPU1_706_WDO Width:4.8mil Length:40.245mil)","Track (3479.607mil,191.574mil)(3867.426mil,191.574mil) on L8","Track: (Net: CPU1_706_WDO Width:4.8mil Length:387.819mil)","Track (4114.749mil,121.612mil)(4768.612mil,121.612mil) on L8","Track: (Net: CPU1_706_WDO Width:4.8mil Length:653.863mil)","Track (3462.128mil,209.053mil)(3462.128mil,248.86mil) on L8","Track: (Net: CPU1_706_WDO Width:4.8mil Length:39.807mil)","Track (3462.128mil,248.86mil)(3479.528mil,266.26mil) on L8","Track: (Net: CPU1_706_WDO Width:4.8mil Length:24.607mil)","Track (6072.993mil,2314.68mil)(6072.993mil,2724.69mil) on L8","Track: (Net: CPU1_706_WDI Width:4.8mil Length:410.009mil)","Track (6013.938mil,2755.906mil)(6033.623mil,2736.221mil) on L8","Track: (Net: CPU1_706_WDI Width:4.8mil Length:27.839mil)","Track (5164.4mil,870.212mil)(5222.388mil,928.2mil) on L8","Track: (Net: CPU1_706_WDI Width:4.8mil Length:82.007mil)","Track (5069.6mil,442.965mil)(5164.4mil,537.765mil) on L8","Track: (Net: CPU1_706_WDI Width:4.8mil Length:134.067mil)","Track (4967.278mil,179.643mil)(4967.278mil,196.894mil) on L8","Track: (Net: CPU1_706_WDI Width:4.8mil Length:17.251mil)","Track (3808.651mil,107.212mil)(4894.847mil,107.212mil) on L8","Track: (Net: CPU1_706_WDI Width:4.8mil Length:1086.196mil)","Track (3781.863mil,134mil)(3808.651mil,107.212mil) on L8","Track: (Net: CPU1_706_WDI Width:4.8mil Length:37.884mil)","Track (3479.528mil,166.26mil)(3511.788mil,134mil) on L8","Track: (Net: CPU1_706_WDI Width:4.8mil Length:45.623mil)","Track (6072.993mil,2747.752mil)(6084.524mil,2736.221mil) on L8","Track (6100.832mil,2736.221mil)(6112.363mil,2724.69mil) on L8","Track (6013.938mil,2795.276mil)(6033.623mil,2775.591mil) on L8","Track: (Net: CPU1_706_MR Width:4.8mil Length:27.839mil)","Track (5178.8mil,863.8mil)(5228.8mil,913.8mil) on L8","Track: (Net: CPU1_706_MR Width:4.8mil Length:70.711mil)","Track (5084mil,293.251mil)(5084mil,437mil) on L8","Track: (Net: CPU1_706_MR Width:4.8mil Length:143.749mil)","Track (4981.678mil,190.929mil)(5084mil,293.251mil) on L8","Track: (Net: CPU1_706_MR Width:4.8mil Length:144.705mil)","Track (3262.992mil,242.655mil)(3310.525mil,195.122mil) on L8","Track: (Net: CPU1_706_MR Width:4.8mil Length:67.222mil)","Track (4981.678mil,173.678mil)(4981.678mil,190.929mil) on L8","Track: (Net: CPU1_706_MR Width:4.8mil Length:17.251mil)","Track (3431.981mil,72.412mil)(4880.412mil,72.412mil) on L8","Track: (Net: CPU1_706_MR Width:4.8mil Length:1448.431mil)","Track (5781.933mil,2141.732mil)(5797.401mil,2157.2mil) on L8","Track: (Net: 7998_CONVST Width:4.8mil Length:21.875mil)","Track (5433.36mil,1911.269mil)(5679.291mil,2157.2mil) on L8","Track: (Net: 1V05PGOOD_TEMP Width:4.8mil Length:347.799mil)","Track (5808.932mil,2185.039mil)(5825.24mil,2185.039mil) on L8","Track: (Net: 7998_CONVST Width:4.8mil Length:16.307mil)","Track (5836.771mil,2196.57mil)(5836.771mil,2212.877mil) on L8","Track (5836.771mil,2212.877mil)(5848.303mil,2224.409mil) on L8","Track: (Net: 7998_CONVST Width:4.8mil Length:16.308mil)","Track (5864.61mil,2224.409mil)(5895.827mil,2255.626mil) on L8","Track: (Net: 7998_CONVST Width:4.8mil Length:44.148mil)","Track (5895.827mil,2271.932mil)(5927.044mil,2303.149mil) on L8","Track (5954.883mil,2314.68mil)(5954.883mil,2685.32mil) on L8","Track: (Net: 7998_CONVST Width:4.8mil Length:370.639mil)","Track (5785.87mil,2185.039mil)(5797.401mil,2196.57mil) on L8","Track: (Net: 7998_ALERT Width:4.8mil Length:16.308mil)","Track (5808.932mil,2224.409mil)(5825.24mil,2224.409mil) on L8","Track: (Net: 7998_ALERT Width:4.8mil Length:16.307mil)","Track (5836.771mil,2235.94mil)(5836.771mil,2252.247mil) on L8","Track (5836.771mil,2252.247mil)(5848.303mil,2263.779mil) on L8","Track (5758.031mil,2157.2mil)(5758.031mil,2173.508mil) on L8","Track (5769.562mil,2185.039mil)(5785.87mil,2185.039mil) on L8","Track (5915.513mil,2314.682mil)(5915.513mil,2724.69mil) on L8","Track: (Net: 7998_ALERT Width:4.8mil Length:410.007mil)","Track (5808.932mil,2263.779mil)(5825.24mil,2263.779mil) on L8","Track: (Net: 1V5PGOOD_TEMP Width:4.8mil Length:16.307mil)","Track (5876.141mil,2303.149mil)(5895.826mil,2322.834mil) on L8","Track: (Net: 1V5PGOOD_TEMP Width:4.8mil Length:27.839mil)","Track (5690.822mil,2185.039mil)(5707.13mil,2185.039mil) on L8","Track: (Net: 1V05PGOOD_TEMP Width:4.8mil Length:16.307mil)","Track (5730.192mil,2224.409mil)(5746.5mil,2224.409mil) on L8","Track (5769.562mil,2263.779mil)(5785.87mil,2263.779mil) on L8","Track (5797.401mil,2291.618mil)(5808.932mil,2303.149mil) on L8","Track: (Net: 1V05PGOOD_TEMP Width:4.8mil Length:16.308mil)","Track (5785.87mil,2263.779mil)(5797.401mil,2275.31mil) on L8","Track (5808.932mil,2303.149mil)(5825.24mil,2303.149mil) on L8","Track (5848.302mil,2342.519mil)(5864.61mil,2342.519mil) on L8","Track (5746.5mil,2224.409mil)(5758.031mil,2235.94mil) on L8","Track (5836.771mil,2330.988mil)(5848.302mil,2342.519mil) on L8","Track (5895.826mil,2373.735mil)(5895.826mil,2598.426mil) on L8","Track: (Net: 1V05PGOOD_TEMP Width:4.8mil Length:224.691mil)","Track (5718.661mil,2173.508mil)(5730.192mil,2185.039mil) on L8","Track: (Net: 1V5PGOOD_TEMP Width:4.8mil Length:16.308mil)","Track (5730.192mil,2185.039mil)(5746.5mil,2185.039mil) on L8","Track (5758.031mil,2196.57mil)(5758.031mil,2212.878mil) on L8","Track (5769.562mil,2224.409mil)(5785.87mil,2224.409mil) on L8","Track (5797.401mil,2235.94mil)(5797.401mil,2252.248mil) on L8","Track (5836.771mil,2291.618mil)(5848.302mil,2303.149mil) on L8","Track (5994.253mil,2708.382mil)(5994.253mil,2775.591mil) on L8","Track: (Net: 7998_CONVST Width:4.8mil Length:67.209mil)","Track (5966.414mil,2696.851mil)(5982.722mil,2696.851mil) on L8","Track (5121.2mil,802.277mil)(5121.2mil,888.106mil) on L8","Track: (Net: 7998_CONVST Width:4.8mil Length:85.829mil)","Track (4877.033mil,558.11mil)(5121.2mil,802.277mil) on L8","Track: (Net: 7998_CONVST Width:4.8mil Length:345.304mil)","Track (4754.645mil,558.11mil)(4877.033mil,558.11mil) on L8","Track: (Net: 7998_CONVST Width:4.8mil Length:122.388mil)","Track (4554.645mil,458.11mil)(4617.845mil,521.31mil) on L8","Track: (Net: 7998_CONVST Width:4.8mil Length:89.378mil)","Track (4255.01mil,458.11mil)(4554.645mil,458.11mil) on L8","Track: (Net: 7998_CONVST Width:4.8mil Length:299.635mil)","Track (3966.77mil,250.354mil)(4043.546mil,327.13mil) on L8","Track: (Net: 7998_CONVST Width:4.8mil Length:108.578mil)","Track (5927.044mil,2736.221mil)(5954.883mil,2736.221mil) on L8","Track: (Net: 7998_ALERT Width:4.8mil Length:27.839mil)","Track (5106.8mil,894.071mil)(5198.529mil,985.8mil) on L8","Track: (Net: 7998_ALERT Width:4.8mil Length:129.725mil)","Track (4882.612mil,589.71mil)(5106.8mil,813.898mil) on L8","Track: (Net: 7998_ALERT Width:4.8mil Length:317.05mil)","Track (4869.412mil,576.51mil)(4882.612mil,589.71mil) on L8","Track: (Net: 7998_ALERT Width:4.8mil Length:18.668mil)","Track (4747.023mil,576.51mil)(4869.412mil,576.51mil) on L8","Track: (Net: 7998_ALERT Width:4.8mil Length:122.388mil)","Track (4578.623mil,508.11mil)(4610.223mil,539.71mil) on L8","Track: (Net: 7998_ALERT Width:4.8mil Length:44.689mil)","Track (4252.976mil,508.11mil)(4578.623mil,508.11mil) on L8","Track: (Net: 7998_ALERT Width:4.8mil Length:325.647mil)","Track (3940.195mil,250.354mil)(4089.816mil,399.974mil) on L8","Track: (Net: 7998_ALERT Width:4.8mil Length:211.595mil)","Track (5192.565mil,1000.2mil)(5386.515mil,1000.2mil) on L8","Track: (Net: 1V5PGOOD_TEMP Width:4.8mil Length:193.95mil)","Track (5092.4mil,825.52mil)(5092.4mil,900.035mil) on L8","Track: (Net: 1V5PGOOD_TEMP Width:4.8mil Length:74.516mil)","Track (4864.88mil,598mil)(5092.4mil,825.52mil) on L8","Track: (Net: 1V5PGOOD_TEMP Width:4.8mil Length:321.762mil)","Track (4204.11mil,558.11mil)(4702.602mil,558.11mil) on L8","Track: (Net: 1V5PGOOD_TEMP Width:4.8mil Length:498.492mil)","Track (4012.5mil,538.78mil)(4184.78mil,538.78mil) on L8","Track: (Net: 1V5PGOOD_TEMP Width:4.8mil Length:172.28mil)","Track (5078mil,831.484mil)(5078mil,906mil) on L8","Track: (Net: 1V05PGOOD_TEMP Width:4.8mil Length:74.516mil)","Track (4904.626mil,658.11mil)(5078mil,831.484mil) on L8","Track: (Net: 1V05PGOOD_TEMP Width:4.8mil Length:245.188mil)","Track (6281.098mil,3376.97mil)(6281.098mil,3454.97mil) on L8","Track: (Net: $330N1514 Width:15mil Length:78mil)","Track (6434.37mil,310mil)(6545mil,199.37mil) on L8","Track: (Net: CPU1_JTAG_HRESET Width:4.8mil Length:156.454mil)","Track (6434.37mil,360mil)(6595mil,199.37mil) on L8","Track: (Net: CPU1_JTAG_SRESET Width:4.8mil Length:227.165mil)","Track (5940.339mil,2851.6mil)(6269.416mil,2851.6mil) on L8","Track: (Net: CDI_0 Width:4.8mil Length:329.077mil)","Track (6402.942mil,2698.495mil)(6543mil,2558.437mil) on L8","Track: (Net: CDI_0 Width:4.8mil Length:198.072mil)","Track (6475.791mil,2350.209mil)(6475.791mil,2529.209mil) on L8","Track: (Net: CPU1_JTAG_TRST Width:4.8mil Length:179mil)","Track (6388.542mil,2616.458mil)(6475.791mil,2529.209mil) on L8","Track: (Net: CPU1_JTAG_TRST Width:4.8mil Length:123.389mil)","Track (6339mil,2362.437mil)(6371.437mil,2330mil) on L8","Track: (Net: CPU1_ETH1_INT_N Width:4.8mil Length:45.872mil)","Track (6371.437mil,2330mil)(6392.536mil,2330mil) on L8","Track: (Net: CPU1_ETH1_INT_N Width:4.8mil Length:21.099mil)","Track (6403.742mil,2339.159mil)(6850.124mil,1892.777mil) on L8","Track: (Net: CPU1_ETH1_RESET_N Width:4.8mil Length:631.279mil)","Track (6850.124mil,1447.214mil)(6850.124mil,1892.777mil) on L8","Track: (Net: CPU1_ETH1_RESET_N Width:4.8mil Length:445.562mil)","Track (6094.35mil,3401.422mil)(6110.098mil,3385.674mil) on L8","Track: (Net: AD936x_1_RESETB Width:4.8mil Length:22.271mil)","Track (6031.356mil,3401.422mil)(6047.104mil,3385.674mil) on L8","Track: (Net: AD936x_1_SYNC Width:4.8mil Length:22.271mil)","Track (5291.976mil,3862.4mil)(5966.6mil,3862.4mil) on L8","Track: (Net: AD936x_1_SPI_CLK Width:4.8mil Length:674.624mil)","Track (6059.942mil,3702.718mil)(6059.942mil,3745.694mil) on L8","Track: (Net: AD936x_1_CLKOUT Width:4.8mil Length:42.976mil)","Track (5585.189mil,3585.898mil)(5761.618mil,3585.898mil) on L8","Track: (Net: AD936x_1_TX_D1_P Width:4mil Length:176.429mil)","Track (5571.578mil,3599.509mil)(5571.578mil,3599.51mil) on L8","Track: (Net: AD936x_1_TX_D1_P Width:4mil Length:0mil)","Track (4800.596mil,3602mil)(4803.96mil,3605.364mil) on L8","Track: (Net: AD936x_1_TX_D1_N Width:4mil Length:4.757mil)","Track (5580.578mil,3603.237mil)(5580.578mil,3603.238mil) on L8","Track: (Net: AD936x_1_TX_D1_N Width:4mil Length:0mil)","Track (5565.347mil,3618.468mil)(5580.578mil,3603.238mil) on L8","Track: (Net: AD936x_1_TX_D1_N Width:4mil Length:21.539mil)","Track (4804.324mil,3593mil)(4820.792mil,3609.468mil) on L8","Track: (Net: AD936x_1_TX_D1_P Width:4mil Length:23.289mil)","Track (4803.96mil,3605.364mil)(4803.96mil,3605.364mil) on L8","Track (4541.022mil,3588.512mil)(4554.51mil,3602mil) on L8","Track: (Net: AD936x_1_TX_D1_N Width:4mil Length:19.075mil)","Track (4558.238mil,3593mil)(4676.781mil,3593mil) on L8","Track: (Net: AD936x_1_TX_D1_P Width:4mil Length:118.543mil)","Track (4680.509mil,3602mil)(4680.509mil,3602mil) on L8","Track (4676.781mil,3593mil)(4676.781mil,3593mil) on L8","Track (3147.648mil,3459.11mil)(4137.382mil,3459.11mil) on L8","Track: (Net: AD936x_1_TX_D0_P Width:4mil Length:989.734mil)","Track (4318.11mil,3627.11mil)(4554.938mil,3627.11mil) on L8","Track: (Net: AD936x_1_TX_D0_N Width:4mil Length:236.828mil)","Track (4141.11mil,3450.11mil)(4318.11mil,3627.11mil) on L8","Track: (Net: AD936x_1_TX_D0_N Width:4mil Length:250.316mil)","Track (3950.409mil,3513mil)(4139.272mil,3513mil) on L8","Track: (Net: AD936x_1_TX_D2_N Width:4mil Length:188.863mil)","Track (4293.11mil,3654.11mil)(4789.066mil,3654.11mil) on L8","Track: (Net: AD936x_1_TX_D2_P Width:4mil Length:495.956mil)","Track (4139.272mil,3513mil)(4289.382mil,3663.11mil) on L8","Track: (Net: AD936x_1_TX_D2_N Width:4mil Length:212.288mil)","Track (3978.953mil,3567mil)(4156mil,3567mil) on L8","Track: (Net: AD936x_1_FB_CLK_P Width:4mil Length:177.047mil)","Track (4156mil,3567mil)(4272.842mil,3683.842mil) on L8","Track: (Net: AD936x_1_FB_CLK_P Width:4mil Length:165.239mil)","Track (4152.272mil,3576mil)(4269.114mil,3692.842mil) on L8","Track: (Net: AD936x_1_FB_CLK_N Width:4mil Length:165.239mil)","Track (3981.769mil,3608mil)(4140.272mil,3608mil) on L8","Track: (Net: AD936x_1_DATA_CLK_P Width:4mil Length:158.503mil)","Track (4144mil,3608mil)(4252mil,3716mil) on L8","Track: (Net: AD936x_1_DATA_CLK_P Width:4mil Length:152.735mil)","Track (4140.272mil,3608mil)(4140.272mil,3608mil) on L8","Track: (Net: AD936x_1_DATA_CLK_P Width:4mil Length:0mil)","Track (4252mil,3716mil)(4576mil,3716mil) on L8","Track: (Net: AD936x_1_DATA_CLK_P Width:4mil Length:324mil)","Track (4374.512mil,3588.512mil)(4541.022mil,3588.512mil) on L8","Track: (Net: AD936x_1_TX_D1_N Width:4mil Length:166.51mil)","Track (4200.882mil,3450.318mil)(4249.046mil,3450.318mil) on L8","Track: (Net: AD936x_1_TX_D1_P Width:4mil Length:48.164mil)","Track (4245.318mil,3459.318mil)(4374.512mil,3588.512mil) on L8","Track: (Net: AD936x_1_TX_D1_N Width:4mil Length:182.708mil)","Track (3927.247mil,3477.11mil)(3954.137mil,3504mil) on L8","Track: (Net: AD936x_1_TX_D2_P Width:4mil Length:38.028mil)","Track (3936.769mil,3563mil)(3981.769mil,3608mil) on L8","Track: (Net: AD936x_1_DATA_CLK_P Width:4mil Length:63.639mil)","Track (5019.746mil,3786.254mil)(5041mil,3765mil) on L8","Track: (Net: AD936x_1_DATA_CLK_N Width:4mil Length:30.057mil)","Track (5316.036mil,3765mil)(5343.654mil,3792.618mil) on L8","Track: (Net: AD936x_1_DATA_CLK_N Width:4mil Length:39.058mil)","Track (5319.764mil,3756mil)(5347.382mil,3783.618mil) on L8","Track: (Net: AD936x_1_DATA_CLK_P Width:4mil Length:39.058mil)","Track (5000.684mil,3864.336mil)(5072.731mil,3792.288mil) on L8","Track: (Net: AD936x_1_CLKOUT Width:4.8mil Length:101.891mil)","Track (4749.949mil,3850.71mil)(4777.975mil,3878.736mil) on L8","Track: (Net: AD936x_1_SPI_CLK Width:4.8mil Length:39.635mil)","Track (4750.999mil,3807mil)(4808.335mil,3864.336mil) on L8","Track: (Net: AD936x_1_CLKOUT Width:4.8mil Length:81.085mil)","Track (4777.975mil,3878.736mil)(5006.648mil,3878.736mil) on L8","Track: (Net: AD936x_1_SPI_CLK Width:4.8mil Length:228.673mil)","Track (4320.406mil,3847mil)(4366.542mil,3893.136mil) on L8","Track: (Net: AD936x_1_SPI_DO Width:4.8mil Length:65.246mil)","Track (4329.55mil,3815.416mil)(4364.844mil,3850.71mil) on L8","Track: (Net: AD936x_1_SPI_CLK Width:4.8mil Length:49.913mil)","Track (4816.408mil,3819.816mil)(4973.456mil,3819.816mil) on L8","Track: (Net: AD936x_1_DATA_CLK_P Width:4mil Length:157.048mil)","Track (4740.592mil,3744mil)(4816.408mil,3819.816mil) on L8","Track: (Net: AD936x_1_DATA_CLK_P Width:4mil Length:107.22mil)","Track (4736.864mil,3753mil)(4812.681mil,3828.816mil) on L8","Track: (Net: AD936x_1_DATA_CLK_N Width:4mil Length:107.22mil)","Track (4604mil,3744mil)(4740.592mil,3744mil) on L8","Track: (Net: AD936x_1_DATA_CLK_P Width:4mil Length:136.592mil)","Track (5078.696mil,3806.688mil)(5236.264mil,3806.688mil) on L8","Track: (Net: AD936x_1_SPI_CLK Width:4.8mil Length:157.568mil)","Track (5084.661mil,3821.088mil)(5230.299mil,3821.088mil) on L8","Track: (Net: AD936x_1_SPI_DO Width:4.8mil Length:145.639mil)","Track (5236.264mil,3806.688mil)(5291.976mil,3862.4mil) on L8","Track: (Net: AD936x_1_SPI_CLK Width:4.8mil Length:78.788mil)","Track (5230.299mil,3821.088mil)(5286.011mil,3876.8mil) on L8","Track: (Net: AD936x_1_SPI_DO Width:4.8mil Length:78.788mil)","Track (6078.602mil,3417.17mil)(6078.602mil,3457.891mil) on L8","Track: (Net: AD936x_1_SPI_CLK Width:4.8mil Length:40.721mil)","Track (5916.883mil,996mil)(6010.972mil,996mil) on L8","Track: (Net: 3V3PGOOD_TEMP Width:4.8mil Length:94.089mil)","Track (5824.4mil,1010.4mil)(6005.007mil,1010.4mil) on L8","Track: (Net: 1V4PGOOD_TEMP Width:4.8mil Length:180.607mil)","Track (5791.157mil,918mil)(5838.883mil,918mil) on L8","Track: (Net: 3V3PGOOD_TEMP Width:4.8mil Length:47.726mil)","Track (5600mil,624mil)(5711mil,735mil) on L8","Track: (Net: 3V3PGOOD_TEMP Width:4.8mil Length:156.978mil)","Track (5605mil,768.384mil)(5605mil,837.393mil) on L8","Track: (Net: 1V4PGOOD_TEMP Width:4.8mil Length:69.008mil)","Track (5605mil,837.393mil)(5688.05mil,920.442mil) on L8","Track: (Net: 1V4PGOOD_TEMP Width:4.8mil Length:117.45mil)","Track (6211.424mil,1911.378mil)(6214mil,1911.378mil) on L8","Track: (Net: CPU1_A29 Width:4.8mil Length:2.576mil)","Track (6207.824mil,1914.978mil)(6207.824mil,1914.979mil) on L8","Track: (Net: CPU1_A29 Width:4.8mil Length:0.001mil)","Track (6197.024mil,1918.579mil)(6204.224mil,1918.579mil) on L8","Track: (Net: CPU1_A29 Width:4.8mil Length:7.2mil)","Track (6193.424mil,1893.476mil)(6193.424mil,1914.979mil) on L8","Track: (Net: CPU1_A29 Width:4.8mil Length:21.503mil)","Track (6182.624mil,1889.876mil)(6189.824mil,1889.876mil) on L8","Track (6179.024mil,1893.476mil)(6179.024mil,1921.358mil) on L8","Track: (Net: CPU1_A29 Width:4.8mil Length:27.881mil)","Track (6168.224mil,1924.958mil)(6175.424mil,1924.958mil) on L8","Track (6164.624mil,1887.526mil)(6164.624mil,1921.358mil) on L8","Track: (Net: CPU1_A29 Width:4.8mil Length:33.831mil)","Track (6153.824mil,1883.926mil)(6161.024mil,1883.926mil) on L8","Track (6150.224mil,1887.526mil)(6150.224mil,1921.358mil) on L8","Track (6139.424mil,1924.958mil)(6146.624mil,1924.958mil) on L8","Track (6135.824mil,1894.824mil)(6135.824mil,1921.358mil) on L8","Track: (Net: CPU1_A29 Width:4.8mil Length:26.534mil)","Track (6118.6mil,1877.6mil)(6133.423mil,1892.423mil) on L8","Track: (Net: CPU1_A29 Width:4.8mil Length:20.963mil)","Track (221.531mil,2236.741mil)(221.531mil,2252.682mil) on L8","Track: (Net: AFDX2_RX+ Width:4mil Length:15.941mil)","Track (239.528mil,2270.678mil)(239.528mil,2279.163mil) on L8","Track: (Net: AFDX2_RX+ Width:4mil Length:8.485mil)","Track (222.557mil,2287.648mil)(231.043mil,2287.648mil) on L8","Track (188.62mil,2269.652mil)(204.561mil,2269.652mil) on L8","Track (230.531mil,2240.468mil)(239.119mil,2231.88mil) on L8","Track: (Net: AFDX2_RX- Width:4mil Length:12.145mil)","Track (230.531mil,2248.954mil)(248.528mil,2266.95mil) on L8","Track: (Net: AFDX2_RX- Width:4mil Length:25.451mil)","Track (234.77mil,2296.648mil)(248.528mil,2282.891mil) on L8","Track: (Net: AFDX2_RX- Width:4mil Length:19.456mil)","Track (200.833mil,2278.652mil)(218.829mil,2296.648mil) on L8","Track (189.069mil,2281.931mil)(192.348mil,2278.652mil) on L8","Track: (Net: AFDX2_RX- Width:4mil Length:4.637mil)","Track (162mil,2309mil)(189.069mil,2281.931mil) on L8","Track: (Net: AFDX2_RX- Width:4mil Length:38.282mil)","Track (239.12mil,2231.88mil)(302.728mil,2168.272mil) on L8","Track: (Net: AFDX2_RX- Width:4mil Length:89.956mil)","Track (302.73mil,2142.154mil)(324.804mil,2120.08mil) on L8","Track: (Net: AFDX2_RX- Width:4mil Length:31.217mil)","Track (6170.006mil,1610.218mil)(6173.606mil,1613.818mil) on L8","Track (6170.006mil,1605.127mil)(6173.124mil,1602.008mil) on L8","Track: (Net: CPU1_A22 Width:4.8mil Length:4.41mil)","Track (6168.033mil,1591.826mil)(6173.124mil,1596.917mil) on L8","Track: (Net: CPU1_A22 Width:4.8mil Length:7.2mil)","Track (6153.28mil,1601.488mil)(6162.942mil,1591.826mil) on L8","Track: (Net: CPU1_A22 Width:4.8mil Length:13.664mil)","Track (6143.098mil,1596.397mil)(6148.189mil,1601.488mil) on L8","Track (6143.098mil,1591.305mil)(6169.792mil,1564.612mil) on L8","Track: (Net: CPU1_A22 Width:4.8mil Length:37.751mil)","Track (6164.7mil,1554.43mil)(6169.792mil,1559.521mil) on L8","Track (6132.916mil,1581.123mil)(6159.609mil,1554.43mil) on L8","Track (6122.733mil,1576.032mil)(6127.824mil,1581.123mil) on L8","Track (6122.733mil,1570.941mil)(6149.427mil,1544.247mil) on L8","Track (6144.336mil,1534.065mil)(6149.427mil,1539.156mil) on L8","Track (6112.551mil,1560.758mil)(6139.244mil,1534.065mil) on L8","Track (6102.368mil,1555.667mil)(6107.46mil,1560.758mil) on L8","Track (6102.368mil,1550.576mil)(6129.062mil,1523.882mil) on L8","Track (6123.971mil,1513.7mil)(6129.062mil,1518.791mil) on L8","Track (6092.186mil,1540.394mil)(6118.88mil,1513.7mil) on L8","Track (6082.004mil,1535.303mil)(6087.095mil,1540.394mil) on L8","Track (6082.004mil,1530.211mil)(6108.698mil,1503.518mil) on L8","Track (6103.606mil,1493.335mil)(6108.698mil,1498.427mil) on L8","Track (6073.943mil,1517.908mil)(6098.515mil,1493.335mil) on L8","Track: (Net: CPU1_A22 Width:4.8mil Length:34.751mil)","Track (6056.972mil,1506.028mil)(6068.852mil,1517.908mil) on L8","Track: (Net: CPU1_A22 Width:4.8mil Length:16.801mil)","Track (6045.944mil,1495mil)(6056.972mil,1506.028mil) on L8","Track: (Net: CPU1_A22 Width:4.8mil Length:15.596mil)","Track (6231.657mil,1998.536mil)(6231.9mil,1998.294mil) on L8","Track: (Net: CPU1_A12 Width:4.8mil Length:0.343mil)","Track (6205.137mil,1977.108mil)(6226.566mil,1998.536mil) on L8","Track: (Net: CPU1_A12 Width:4.8mil Length:30.305mil)","Track (6194.955mil,1982.199mil)(6200.046mil,1977.108mil) on L8","Track: (Net: CPU1_A12 Width:4.8mil Length:7.2mil)","Track (6194.955mil,1987.29mil)(6251.739mil,2044.074mil) on L8","Track: (Net: CPU1_A12 Width:4.8mil Length:80.305mil)","Track (6246.648mil,2054.256mil)(6251.739mil,2049.165mil) on L8","Track (6157.749mil,1970.449mil)(6241.556mil,2054.256mil) on L8","Track: (Net: CPU1_A12 Width:4.8mil Length:118.521mil)","Track (6147.567mil,1975.541mil)(6152.658mil,1970.449mil) on L8","Track (6147.567mil,1980.632mil)(6231.374mil,2064.439mil) on L8","Track (6226.283mil,2074.621mil)(6231.374mil,2069.53mil) on L8","Track (6137.385mil,1990.814mil)(6221.192mil,2074.621mil) on L8","Track (6127.202mil,1995.905mil)(6132.293mil,1990.814mil) on L8","Track (6127.202mil,2000.996mil)(6211.009mil,2084.803mil) on L8","Track (6205.918mil,2094.986mil)(6211.009mil,2089.895mil) on L8","Track (6117.02mil,2011.179mil)(6200.827mil,2094.986mil) on L8","Track (6106.838mil,2016.27mil)(6111.929mil,2011.179mil) on L8","Track (6106.838mil,2021.361mil)(6190.645mil,2105.168mil) on L8","Track (6185.554mil,2115.35mil)(6190.645mil,2110.259mil) on L8","Track (6096.655mil,2031.543mil)(6180.462mil,2115.35mil) on L8","Track (6086.473mil,2036.634mil)(6091.564mil,2031.543mil) on L8","Track (6086.473mil,2041.726mil)(6170.28mil,2125.533mil) on L8","Track (6165.189mil,2135.715mil)(6170.28mil,2130.624mil) on L8","Track (6076.291mil,2051.908mil)(6160.098mil,2135.715mil) on L8","Track (6066.108mil,2056.999mil)(6071.199mil,2051.908mil) on L8","Track (6066.108mil,2062.09mil)(6133.022mil,2129.004mil) on L8","Track: (Net: CPU1_A12 Width:4.8mil Length:94.631mil)","Track (6127.931mil,2139.187mil)(6133.022mil,2134.096mil) on L8","Track (6109.469mil,2125.815mil)(6122.84mil,2139.187mil) on L8","Track: (Net: CPU1_A12 Width:4.8mil Length:18.91mil)","Track (6104.377mil,2125.816mil)(6104.378mil,2125.815mil) on L8","Track: (Net: CPU1_A12 Width:4.8mil Length:0.001mil)","Track (6072.993mil,2157.2mil)(6102.68mil,2127.513mil) on L8","Track: (Net: CPU1_A12 Width:4.8mil Length:41.984mil)","Track (6155.775mil,1482.764mil)(6162.505mil,1489.495mil) on L8","Track: (Net: CPU1_A18 Width:4.8mil Length:9.519mil)","Track (6155.775mil,1477.673mil)(6173.124mil,1460.323mil) on L8","Track: (Net: CPU1_A18 Width:4.8mil Length:24.536mil)","Track (6168.033mil,1450.141mil)(6173.124mil,1455.232mil) on L8","Track: (Net: CPU1_A18 Width:4.8mil Length:7.2mil)","Track (6144.769mil,1468.313mil)(6162.942mil,1450.141mil) on L8","Track: (Net: CPU1_A18 Width:4.8mil Length:25.7mil)","Track (6134.587mil,1463.222mil)(6139.678mil,1468.313mil) on L8","Track (6134.587mil,1458.131mil)(6173.124mil,1419.594mil) on L8","Track: (Net: CPU1_A18 Width:4.8mil Length:54.5mil)","Track (6168.033mil,1409.411mil)(6173.124mil,1414.502mil) on L8","Track (6124.404mil,1447.949mil)(6162.942mil,1409.411mil) on L8","Track (6114.222mil,1442.858mil)(6119.313mil,1447.949mil) on L8","Track (6114.222mil,1437.766mil)(6162.461mil,1389.528mil) on L8","Track: (Net: CPU1_A18 Width:4.8mil Length:68.219mil)","Track (6157.369mil,1379.346mil)(6162.461mil,1384.437mil) on L8","Track (6104.04mil,1427.584mil)(6152.278mil,1379.346mil) on L8","Track (6093.858mil,1422.493mil)(6098.949mil,1427.584mil) on L8","Track (6093.858mil,1417.402mil)(6121.731mil,1389.528mil) on L8","Track: (Net: CPU1_A18 Width:4.8mil Length:39.419mil)","Track (6116.64mil,1379.346mil)(6121.731mil,1384.437mil) on L8","Track (6084.498mil,1406.396mil)(6111.549mil,1379.346mil) on L8","Track: (Net: CPU1_A18 Width:4.8mil Length:38.255mil)","Track (6068.011mil,1395mil)(6079.407mil,1406.396mil) on L8","Track: (Net: CPU1_A18 Width:4.8mil Length:16.117mil)","Track (5936.4mil,1362.4mil)(6160.825mil,1362.4mil) on L8","Track: (Net: CPU1_A15 Width:4.8mil Length:224.425mil)","Track (6210.47mil,1412.045mil)(6210.47mil,1421.259mil) on L8","Track: (Net: CPU1_A15 Width:4.8mil Length:9.215mil)","Track (6231.633mil,1457.185mil)(6233.07mil,1458.622mil) on L8","Track: (Net: CPU1_A15 Width:4.8mil Length:2.033mil)","Track (6171.003mil,1497.992mil)(6193.07mil,1497.992mil) on L8","Track: (Net: CPU1_A18 Width:4.8mil Length:22.067mil)","Track (6045.944mil,1395mil)(6067.044mil,1395mil) on L8","Track: (Net: CPU1_A18 Width:4.8mil Length:21.1mil)","Track (6215.67mil,1515.392mil)(6233.07mil,1497.992mil) on L8","Track: (Net: CPU1_A17 Width:4.8mil Length:24.607mil)","Track (6185.397mil,1554.762mil)(6215.67mil,1554.762mil) on L8","Track: (Net: CPU1_A19 Width:4.8mil Length:30.273mil)","Track (6058.235mil,1427.6mil)(6185.397mil,1554.762mil) on L8","Track: (Net: CPU1_A19 Width:4.8mil Length:179.834mil)","Track (6232.263mil,1597.225mil)(6233.07mil,1596.418mil) on L8","Track: (Net: CPU1_A22 Width:4.8mil Length:1.142mil)","Track (6182.004mil,1655.667mil)(6202.668mil,1676.332mil) on L8","Track: (Net: CPU1_A23 Width:4.8mil Length:29.224mil)","Track (6146.649mil,1685.931mil)(6176.913mil,1655.667mil) on L8","Track: (Net: CPU1_A23 Width:4.8mil Length:42.8mil)","Track (6136.466mil,1680.84mil)(6141.557mil,1685.931mil) on L8","Track (6136.466mil,1675.749mil)(6173.124mil,1639.091mil) on L8","Track: (Net: CPU1_A23 Width:4.8mil Length:51.843mil)","Track (6168.033mil,1628.909mil)(6173.124mil,1634mil) on L8","Track (6126.284mil,1665.567mil)(6162.942mil,1628.909mil) on L8","Track (6116.101mil,1660.476mil)(6121.193mil,1665.567mil) on L8","Track (6116.101mil,1655.384mil)(6146.366mil,1625.12mil) on L8","Track (6144.668mil,1618.332mil)(6146.366mil,1620.029mil) on L8","Track (6028.544mil,1502.207mil)(6144.668mil,1618.332mil) on L8","Track: (Net: CPU1_A23 Width:4.8mil Length:164.225mil)","Track (5833.2mil,1348.6mil)(5836.801mil,1345mil) on L8","Track: (Net: CPU1_A19 Width:4.8mil Length:5.091mil)","Track (5829.6mil,1357.285mil)(5833.2mil,1353.685mil) on L8","Track (5818.801mil,1353.685mil)(5822.4mil,1357.285mil) on L8","Track (5815.2mil,1309.4mil)(5818.801mil,1313mil) on L8","Track (5804.4mil,1313mil)(5808.001mil,1309.4mil) on L8","Track (5800.801mil,1380.6mil)(5804.4mil,1377mil) on L8","Track (5790.001mil,1377mil)(5793.6mil,1380.6mil) on L8","Track (5786.4mil,1345mil)(5790.001mil,1348.6mil) on L8","Track (5850.716mil,1345mil)(5875.814mil,1345mil) on L8","Track: (Net: CPU1_A19 Width:4.8mil Length:25.098mil)","Track (5875.814mil,1345mil)(5958.414mil,1427.6mil) on L8","Track: (Net: CPU1_A19 Width:4.8mil Length:116.814mil)","Track (6072.993mil,2157.2mil)(6072.993mil,2224.409mil) on L8","Track: (Net: CPU1_A12 Width:4.8mil Length:67.209mil)","Track (6028.544mil,1462.4mil)(6028.544mil,1502.207mil) on L8","Track: (Net: CPU1_A23 Width:4.8mil Length:39.807mil)","Track (5958.414mil,1427.6mil)(6058.235mil,1427.6mil) on L8","Track: (Net: CPU1_A19 Width:4.8mil Length:99.821mil)","Track (6063.344mil,1715.344mil)(6180.199mil,1832.199mil) on L8","Track: (Net: CPU1_A26 Width:4.8mil Length:165.258mil)","Track (6192.631mil,1832.199mil)(6193.07mil,1832.638mil) on L8","Track: (Net: CPU1_A26 Width:4.8mil Length:0.621mil)","Track (6185.863mil,1810.668mil)(6211.1mil,1810.668mil) on L8","Track: (Net: CPU1_A25 Width:4.8mil Length:25.237mil)","Track (6077.744mil,1702.549mil)(6185.863mil,1810.668mil) on L8","Track: (Net: CPU1_A25 Width:4.8mil Length:152.903mil)","Track (6113.097mil,1812.4mil)(6172.705mil,1872.008mil) on L8","Track: (Net: CPU1_A28 Width:4.8mil Length:84.298mil)","Track (5984.765mil,1812.4mil)(6113.097mil,1812.4mil) on L8","Track: (Net: CPU1_A28 Width:4.8mil Length:128.333mil)","Track (5597.482mil,1577.6mil)(5828.544mil,1577.6mil) on L8","Track: (Net: CPU1_DQ01 Width:4.8mil Length:231.062mil)","Track (5696.648mil,1539.648mil)(5719.4mil,1562.4mil) on L8","Track: (Net: CPU1_DQ00 Width:4.8mil Length:32.176mil)","Track (5764.056mil,1295mil)(5848.635mil,1295mil) on L8","Track: (Net: CPU1_A17 Width:4.8mil Length:84.579mil)","Track (5764.056mil,1245mil)(5819mil,1245mil) on L8","Track: (Net: CPU1_A15 Width:4.8mil Length:54.944mil)","Track (5764.056mil,1395mil)(5870.551mil,1395mil) on L8","Track: (Net: CPU1_A24 Width:4.8mil Length:106.495mil)","Track (6120.304mil,440.163mil)(6120.304mil,1054.77mil) on L8","Track: (Net: 2V5PGOOD_TEMP Width:4.8mil Length:614.607mil)","Track (6028.544mil,1462.4mil)(6045.944mil,1445mil) on L8","Track: (Net: CPU1_A23 Width:4.8mil Length:24.607mil)","Track (6211.1mil,1810.668mil)(6233.07mil,1832.638mil) on L8","Track: (Net: CPU1_A25 Width:4.8mil Length:31.07mil)","Track (5764.056mil,1445mil)(5870.551mil,1445mil) on L8","Track: (Net: CPU1_A25 Width:4.8mil Length:106.495mil)","Track (5871.337mil,1545mil)(6176.375mil,1850.038mil) on L8","Track: (Net: CPU1_A27 Width:4.8mil Length:431.389mil)","Track (5870.551mil,1495mil)(6063.344mil,1687.793mil) on L8","Track: (Net: CPU1_A26 Width:4.8mil Length:272.65mil)","Track (5863.344mil,1562.4mil)(6045.944mil,1745mil) on L8","Track: (Net: CPU1_DQ00 Width:4.8mil Length:258.235mil)","Track (5767.365mil,1595mil)(5984.765mil,1812.4mil) on L8","Track: (Net: CPU1_A28 Width:4.8mil Length:307.45mil)","Track (5770.388mil,1618.388mil)(5997mil,1845mil) on L8","Track: (Net: CPU1_DQ02 Width:4.8mil Length:320.478mil)","Track (5997mil,1845mil)(6045.944mil,1845mil) on L8","Track: (Net: CPU1_DQ02 Width:4.8mil Length:48.944mil)","Track (5696.851mil,1653.188mil)(5938.663mil,1895mil) on L8","Track: (Net: CPU1_DQ03 Width:4.8mil Length:341.974mil)","Track (5576.93mil,1517.678mil)(5598.9mil,1539.648mil) on L8","Track: (Net: CPU1_DQ00 Width:4.8mil Length:31.07mil)","Track (5576.93mil,1596.418mil)(5598.9mil,1618.388mil) on L8","Track: (Net: CPU1_DQ02 Width:4.8mil Length:31.07mil)","Track (5593.13mil,1636.595mil)(5609.723mil,1653.188mil) on L8","Track: (Net: CPU1_DQ03 Width:4.8mil Length:23.466mil)","Track (5577.737mil,1636.595mil)(5593.13mil,1636.595mil) on L8","Track: (Net: CPU1_DQ03 Width:4.8mil Length:15.393mil)","Track (5616.93mil,1675.158mil)(5669.607mil,1675.158mil) on L8","Track: (Net: CPU1_DQ04 Width:4.8mil Length:52.677mil)","Track (5756.849mil,1762.4mil)(5776.428mil,1762.4mil) on L8","Track: (Net: CPU1_DQ04 Width:4.8mil Length:19.579mil)","Track (4848.7mil,1402.636mil)(4848.7mil,1442.008mil) on L8","Track: (Net: CPU1_TSEC_1588_ALARM_OUT01 Width:4.8mil Length:39.372mil)","Track (4855.423mil,1384.752mil)(4868mil,1397.329mil) on L8","Track: (Net: CPU1_IIC1_SCL Width:4.8mil Length:17.786mil)","Track (4855.214mil,1384.752mil)(4855.423mil,1384.752mil) on L8","Track: (Net: CPU1_IIC1_SCL Width:4.8mil Length:0.209mil)","Track (4836.586mil,1365.915mil)(4836.586mil,1366.124mil) on L8","Track (4905.47mil,1414.434mil)(4905.47mil,1448.47mil) on L8","Track: (Net: CPU1_IIC1_SDA Width:4.8mil Length:34.036mil)","Track (4861.388mil,1370.352mil)(4905.47mil,1414.434mil) on L8","Track: (Net: CPU1_IIC1_SDA Width:4.8mil Length:62.342mil)","Track (6046.63mil,320.118mil)(6125.602mil,241.146mil) on L8","Track: (Net: +5V Width:15mil Length:111.683mil)","Track (3093mil,3171.728mil)(3096mil,3174.728mil) on L8","Track: (Net: AD936x_1_TX_FRAME_P Width:4mil Length:4.243mil)","Track (3096mil,3174.728mil)(3102.272mil,3181mil) on L8","Track: (Net: AD936x_1_TX_FRAME_P Width:4mil Length:8.87mil)","Track (3093mil,2702.24mil)(3093mil,3171.728mil) on L8","Track: (Net: AD936x_1_TX_FRAME_P Width:4mil Length:469.488mil)","Track (3102mil,2698.512mil)(3102mil,3168mil) on L8","Track: (Net: AD936x_1_TX_FRAME_N Width:4mil Length:469.488mil)","Track (5385.73mil,3369mil)(5494.072mil,3477.342mil) on L8","Track: (Net: AD936x_1_TX_D3_P Width:4mil Length:153.219mil)","Track (3021mil,3243.367mil)(3146.633mil,3369mil) on L8","Track: (Net: AD936x_1_TX_D3_P Width:4mil Length:177.671mil)","Track (3026.682mil,3210.865mil)(3048mil,3232.183mil) on L8","Track: (Net: AD936x_1_TX_D4_P Width:4mil Length:30.148mil)","Track (3048mil,3232.184mil)(3157.816mil,3342mil) on L8","Track: (Net: AD936x_1_TX_D4_P Width:4mil Length:155.304mil)","Track (3157.816mil,3342mil)(5535.298mil,3342mil) on L8","Track: (Net: AD936x_1_TX_D4_P Width:4mil Length:2377.482mil)","Track (3040mil,2636.512mil)(3096mil,2692.512mil) on L8","Track: (Net: AD936x_1_TX_FRAME_N Width:4mil Length:79.196mil)","Track (3039mil,3235.912mil)(3154.088mil,3351mil) on L8","Track: (Net: AD936x_1_TX_D4_N Width:4mil Length:162.759mil)","Track (3066mil,3224.728mil)(3165.272mil,3324mil) on L8","Track: (Net: AD936x_1_TX_D5_N Width:4mil Length:140.392mil)","Track (2999.682mil,3222.048mil)(3021mil,3243.366mil) on L8","Track: (Net: AD936x_1_TX_D3_P Width:4mil Length:30.148mil)","Track (3039mil,3235.91mil)(3039mil,3235.912mil) on L8","Track: (Net: AD936x_1_TX_D4_N Width:4mil Length:0.001mil)","Track (5535.298mil,3342mil)(5655mil,3461.702mil) on L8","Track: (Net: AD936x_1_TX_D4_P Width:4mil Length:169.284mil)","Track (5655mil,3461.702mil)(5655mil,3461.704mil) on L8","Track: (Net: AD936x_1_TX_D4_P Width:4mil Length:0.002mil)","Track (3012mil,3247.094mil)(3012mil,3247.095mil) on L8","Track: (Net: AD936x_1_TX_D3_N Width:4mil Length:0.001mil)","Track (3075mil,2709.696mil)(3075mil,3221mil) on L8","Track: (Net: AD936x_1_TX_D5_P Width:4mil Length:511.304mil)","Track (3021mil,3243.366mil)(3021mil,3243.367mil) on L8","Track: (Net: AD936x_1_TX_D3_P Width:4mil Length:0.001mil)","Track (3031mil,2640.24mil)(3093mil,2702.24mil) on L8","Track: (Net: AD936x_1_TX_FRAME_P Width:4mil Length:87.681mil)","Track (3031mil,2364mil)(3031mil,2640.24mil) on L8","Track: (Net: AD936x_1_TX_FRAME_P Width:4mil Length:276.24mil)","Track (2967mil,2614.424mil)(3066mil,2713.424mil) on L8","Track: (Net: AD936x_1_TX_D5_N Width:4mil Length:140.007mil)","Track (2934mil,2179mil)(2934mil,2254.272mil) on L8","Track: (Net: AD936x_1_TX_FRAME_N Width:4mil Length:75.272mil)","Track (2925mil,2182.728mil)(2925mil,2258mil) on L8","Track: (Net: AD936x_1_TX_FRAME_P Width:4mil Length:75.272mil)","Track (2934mil,2254.272mil)(3040mil,2360.272mil) on L8","Track: (Net: AD936x_1_TX_FRAME_N Width:4mil Length:149.906mil)","Track (3105.6mil,2403.993mil)(3105.6mil,2656.6mil) on L8","Track: (Net: AD936x_1_SPI_DI Width:4.8mil Length:252.607mil)","Track (2727.141mil,1893.188mil)(3074.6mil,2240.647mil) on L8","Track: (Net: AD936x_1_SPI_DI Width:4.8mil Length:491.381mil)","Track (2685.006mil,1893.189mil)(2685.007mil,1893.188mil) on L8","Track: (Net: AD936x_1_SPI_DI Width:4.8mil Length:0.001mil)","Track (2668.699mil,1893.189mil)(2685.006mil,1893.189mil) on L8","Track: (Net: AD936x_1_SPI_DI Width:4.8mil Length:16.307mil)","Track (5655mil,3678.532mil)(5736.648mil,3678.532mil) on L8","Track: (Net: AD936x_1_TX_D2_N Width:4mil Length:81.648mil)","Track (5650.5mil,3678.532mil)(5655mil,3678.532mil) on L8","Track: (Net: AD936x_1_TX_D2_N Width:4mil Length:4.5mil)","Track (5655mil,3639.737mil)(5655.933mil,3639.737mil) on L8","Track: (Net: AD936x_1_TX_D0_N Width:4mil Length:0.933mil)","Track (4812.877mil,3639.737mil)(5655mil,3639.737mil) on L8","Track: (Net: AD936x_1_TX_D0_N Width:4mil Length:842.123mil)","Track (4789.066mil,3654.11mil)(4804.488mil,3669.532mil) on L8","Track: (Net: AD936x_1_TX_D2_P Width:4mil Length:21.81mil)","Track (4809.149mil,3648.737mil)(5652.205mil,3648.737mil) on L8","Track: (Net: AD936x_1_TX_D0_P Width:4mil Length:843.056mil)","Track (5650.5mil,3678.532mil)(5650.5mil,3678.532mil) on L8","Track: (Net: AD936x_1_TX_D2_N Width:4mil Length:0mil)","Track (4559.438mil,3627.11mil)(4800.25mil,3627.11mil) on L8","Track: (Net: AD936x_1_TX_D0_N Width:4mil Length:240.812mil)","Track (4785.338mil,3663.11mil)(4800.76mil,3678.532mil) on L8","Track: (Net: AD936x_1_TX_D2_N Width:4mil Length:21.81mil)","Track (4800.76mil,3678.532mil)(5650.5mil,3678.532mil) on L8","Track: (Net: AD936x_1_TX_D2_N Width:4mil Length:849.74mil)","Track (5740.376mil,3669.532mil)(5755.844mil,3685mil) on L8","Track: (Net: AD936x_1_TX_D2_P Width:4mil Length:21.875mil)","Track (5772.346mil,3670.39mil)(5888.372mil,3670.39mil) on L8","Track: (Net: AD936x_1_TX_D0_N Width:4mil Length:116.026mil)","Track (5926.338mil,3701.39mil)(5961.616mil,3666.112mil) on L8","Track: (Net: AD936x_1_TX_D2_N Width:4mil Length:49.891mil)","Track (5983.616mil,3682.294mil)(5983.616mil,3682.296mil) on L8","Track: (Net: AD936x_1_FB_CLK_N Width:4mil Length:0.002mil)","Track (4816.162mil,3719.39mil)(5933.794mil,3719.39mil) on L8","Track: (Net: AD936x_1_FB_CLK_P Width:4mil Length:1117.632mil)","Track (5744.229mil,3655mil)(5768.618mil,3679.39mil) on L8","Track: (Net: AD936x_1_TX_D0_P Width:4mil Length:34.493mil)","Track (5747.956mil,3646mil)(5772.346mil,3670.39mil) on L8","Track: (Net: AD936x_1_TX_D0_N Width:4mil Length:34.493mil)","Track (5755.844mil,3685mil)(5763.234mil,3692.39mil) on L8","Track: (Net: AD936x_1_TX_D2_P Width:4mil Length:10.451mil)","Track (5895.988mil,3675.502mil)(5902.352mil,3669.138mil) on L8","Track: (Net: AD936x_1_TX_D0_P Width:4mil Length:9mil)","Track (5922.61mil,3692.39mil)(5952.616mil,3662.384mil) on L8","Track: (Net: AD936x_1_TX_D2_P Width:4mil Length:42.435mil)","Track (5763.234mil,3692.39mil)(5922.61mil,3692.39mil) on L8","Track: (Net: AD936x_1_TX_D2_P Width:4mil Length:159.376mil)","Track (4791.944mil,3707.9mil)(4812.434mil,3728.39mil) on L8","Track: (Net: AD936x_1_FB_CLK_N Width:4mil Length:28.977mil)","Track (3852.615mil,1424.228mil)(3856.215mil,1427.828mil) on L8","Track: (Net: CPU1_MDQ04 Width:4.8mil Length:5.091mil)","Track (3856.215mil,1431.962mil)(3859.816mil,1435.562mil) on L8","Track (3867.015mil,1435.562mil)(3870.615mil,1431.962mil) on L8","Track (3870.615mil,1414.905mil)(3874.215mil,1411.305mil) on L8","Track (3881.416mil,1411.305mil)(3885.015mil,1414.905mil) on L8","Track (3885.015mil,1435.6mil)(3888.615mil,1439.2mil) on L8","Track (3895.816mil,1439.2mil)(3899.416mil,1435.6mil) on L8","Track (3899.416mil,1414.905mil)(3903.015mil,1411.305mil) on L8","Track (3910.215mil,1411.305mil)(3913.816mil,1414.905mil) on L8","Track (3913.816mil,1435.6mil)(3917.416mil,1439.2mil) on L8","Track (3924.615mil,1439.2mil)(3928.215mil,1435.6mil) on L8","Track (3928.215mil,1414.905mil)(3931.816mil,1411.305mil) on L8","Track (3939.015mil,1411.305mil)(3942.615mil,1414.905mil) on L8","Track (3942.615mil,1435.6mil)(3946.215mil,1439.2mil) on L8","Track (3953.416mil,1439.2mil)(3957.015mil,1435.6mil) on L8","Track (3957.015mil,1414.905mil)(3960.615mil,1411.305mil) on L8","Track (3967.816mil,1411.305mil)(3971.416mil,1414.905mil) on L8","Track (3971.416mil,1435.6mil)(3975.015mil,1439.2mil) on L8","Track (3982.215mil,1439.2mil)(3985.816mil,1435.6mil) on L8","Track (3985.816mil,1431.107mil)(3989.416mil,1427.506mil) on L8","Track (3994.506mil,1427.506mil)(4002.616mil,1435.616mil) on L8","Track: (Net: CPU1_MDQ04 Width:4.8mil Length:11.469mil)","Track (3755.401mil,1399.6mil)(3761.546mil,1399.6mil) on L8","Track: (Net: CPU1_MDQ05 Width:4.8mil Length:6.146mil)","Track (3751.8mil,1403.2mil)(3751.8mil,1415.101mil) on L8","Track: (Net: CPU1_MDQ05 Width:4.8mil Length:11.901mil)","Track (3741.001mil,1418.701mil)(3748.2mil,1418.701mil) on L8","Track: (Net: CPU1_MDQ05 Width:4.8mil Length:7.2mil)","Track (3737.401mil,1394.993mil)(3737.401mil,1415.101mil) on L8","Track: (Net: CPU1_MDQ05 Width:4.8mil Length:20.108mil)","Track (3726.601mil,1391.393mil)(3733.8mil,1391.393mil) on L8","Track (3723.001mil,1394.993mil)(3723.001mil,1422.4mil) on L8","Track: (Net: CPU1_MDQ05 Width:4.8mil Length:27.407mil)","Track (3712.2mil,1426mil)(3719.401mil,1426mil) on L8","Track (3708.601mil,1394.993mil)(3708.601mil,1422.4mil) on L8","Track (3697.8mil,1391.393mil)(3705.001mil,1391.393mil) on L8","Track (3694.2mil,1394.993mil)(3694.2mil,1422.4mil) on L8","Track (3683.401mil,1426mil)(3690.601mil,1426mil) on L8","Track (3679.8mil,1394.993mil)(3679.8mil,1422.4mil) on L8","Track (3669.001mil,1391.393mil)(3676.2mil,1391.393mil) on L8","Track (3665.401mil,1394.993mil)(3665.401mil,1422.4mil) on L8","Track (3654.601mil,1426mil)(3661.8mil,1426mil) on L8","Track (3651.001mil,1403.2mil)(3651.001mil,1422.4mil) on L8","Track: (Net: CPU1_MDQ05 Width:4.8mil Length:19.2mil)","Track (3645mil,1399.6mil)(3647.401mil,1399.6mil) on L8","Track: (Net: CPU1_MDQ05 Width:4.8mil Length:2.401mil)","Track (3771.589mil,1399.6mil)(3780.189mil,1391mil) on L8","Track: (Net: CPU1_MDQ05 Width:4.8mil Length:12.162mil)","Track (3846.601mil,1453.6mil)(3893.573mil,1453.6mil) on L8","Track: (Net: CPU1_MDM00 Width:4.8mil Length:46.972mil)","Track (3843.001mil,1443.559mil)(3843.001mil,1450mil) on L8","Track: (Net: CPU1_MDM00 Width:4.8mil Length:6.441mil)","Track (3832.201mil,1439.959mil)(3839.401mil,1439.959mil) on L8","Track: (Net: CPU1_MDM00 Width:4.8mil Length:7.2mil)","Track (3828.601mil,1443.559mil)(3828.601mil,1505.434mil) on L8","Track: (Net: CPU1_MDM00 Width:4.8mil Length:61.875mil)","Track (3817.801mil,1509.034mil)(3825.001mil,1509.034mil) on L8","Track (3814.201mil,1442.228mil)(3814.201mil,1505.434mil) on L8","Track: (Net: CPU1_MDM00 Width:4.8mil Length:63.206mil)","Track (3803.401mil,1438.628mil)(3810.601mil,1438.628mil) on L8","Track (3799.801mil,1442.228mil)(3799.801mil,1521.234mil) on L8","Track: (Net: CPU1_MDM00 Width:4.8mil Length:79.006mil)","Track (3789.001mil,1524.834mil)(3796.201mil,1524.834mil) on L8","Track (3781.801mil,1453.6mil)(3785.401mil,1457.2mil) on L8","Track: (Net: CPU1_MDM00 Width:4.8mil Length:5.091mil)","Track (4001.281mil,2695.505mil)(4009.088mil,2695.505mil) on L8","Track: (Net: CPU1_MDQ34 Width:4.8mil Length:7.807mil)","Track (3997.681mil,2699.104mil)(3997.681mil,2718.692mil) on L8","Track: (Net: CPU1_MDQ34 Width:4.8mil Length:19.588mil)","Track (3986.881mil,2722.292mil)(3994.081mil,2722.292mil) on L8","Track: (Net: CPU1_MDQ34 Width:4.8mil Length:7.2mil)","Track (3983.281mil,2692.96mil)(3983.281mil,2718.692mil) on L8","Track: (Net: CPU1_MDQ34 Width:4.8mil Length:25.732mil)","Track (3972.481mil,2689.36mil)(3979.681mil,2689.36mil) on L8","Track (3968.881mil,2692.96mil)(3968.881mil,2731.147mil) on L8","Track: (Net: CPU1_MDQ34 Width:4.8mil Length:38.187mil)","Track (3958.081mil,2734.747mil)(3965.281mil,2734.747mil) on L8","Track (3954.481mil,2699.104mil)(3954.481mil,2731.147mil) on L8","Track: (Net: CPU1_MDQ34 Width:4.8mil Length:32.042mil)","Track (3948.48mil,2695.505mil)(3950.881mil,2695.505mil) on L8","Track: (Net: CPU1_MDQ34 Width:4.8mil Length:2.401mil)","Track (3936.848mil,2704.152mil)(3945.495mil,2695.505mil) on L8","Track: (Net: CPU1_MDQ34 Width:4.8mil Length:12.23mil)"]},"meta":{"ts":1767074780647,"source":"AD","rev":0.1,"detail":{"schema":"spec/0.1","build":"ad21-js"}}}